azure_log_analytics_data_collector_api-0.3.0.dist-info/DESCRIPTION.rst
azure_log_analytics_data_collector_api-0.3.0.dist-info/METADATA
azure_log_analytics_data_collector_api-0.3.0.dist-info/RECORD
azure_log_analytics_data_collector_api-0.3.0.dist-info/WHEEL
azure_log_analytics_data_collector_api-0.3.0.dist-info/metadata.json
azure_log_analytics_data_collector_api-0.3.0.dist-info/top_level.txt
datacollectorapi/__init__.py
datacollectorapi/client.py
datacollectorapi/helper.py
datacollectorapi/version.py
