Metadata-Version: 2.0
Name: azure-log-analytics-data-collector-api
Version: 0.3.0
Summary: Azure Log Analytics Data Collector API Client
Home-page: https://github.com/yokawasa/azure-log-analytics-data-collector-python
Author: Yoichi Kawasaki
Author-email: yokawasa@gmail.com
License: MIT
Keywords: azure loganalysis datacollctorapi logs
Platform: any
Classifier: Intended Audience :: Developers
Classifier: License :: OSI Approved :: MIT License
Classifier: Programming Language :: Python
Classifier: Programming Language :: Python :: 2.7
Classifier: Programming Language :: Python :: 3
Classifier: Programming Language :: Python :: 3.3
Classifier: Programming Language :: Python :: 3.4
Classifier: Programming Language :: Python :: 3.5
Classifier: Programming Language :: Python :: 3.6
Classifier: Programming Language :: Python :: 3.7
Classifier: Topic :: Utilities
Requires-Dist: simplejson
